{
  "data": [
    {
      "firstName": "Admin",
      "lastName": "Admin",
      "username": "admin",
      "password": "admin",
      "mail": "admin@gmail.com",
      "id": "8d29"
    },
    {
      "id": "bb94",
      "firstName": "Sudarshan",
      "lastName": "Narhe",
      "username": "SudarshanNarhe",
      "password": "Sudarshan#123",
      "mail": "sudarshannarhe@gmail.com"
    },
    {
      "id": "0be8",
      "firstName": "Suraj",
      "lastName": "Rokade",
      "username": "surajrokade",
      "password": "Suraj#111",
      "mail": "suraj@12gmail.com"
    },
    {
      "id": "c807",
      "firstName": "Yogesh",
      "lastName": "Nawale",
      "username": "yogibaba",
      "password": "Yogibaba@111",
      "mail": "yogi123@gmail.com"
    },
    {
      "id": "dd9d",
      "firstName": "Utkarsha",
      "lastName": "Zambare",
      "username": "utkarshazambare",
      "password": "Utkarsha#111",
      "mail": "utarsha123@gmail.com"
    },
    {
      "id": "f0c8",
      "firstName": "Harshada",
      "lastName": "Patil",
      "username": "harshadapatil",
      "password": "Harshada#111",
      "mail": "harshda@gmail.com"
    },
    {
      "id": "4278",
      "firstName": "User",
      "lastName": "User",
      "username": "User@123",
      "password": "User@123",
      "mail": "user@gmail.com"
    },
    {
      "id": "9478",
      "firstName": "Shubhangi",
      "lastName": "Kolekar",
      "username": "shubhkolekar",
      "password": "Subh@123",
      "mail": "shubh@gmail.com"
    },
    {
      "id": "ee2f",
      "firstname": "Sakshi",
      "lastname": "Narhe",
      "username": "sakshinarhe",
      "password": "Sakshi@123",
      "email": "sakshi@gmail.com",
      "userrole": "User"
    },
    {
      "id": "ee2f",
      "firstname": "Admin",
      "lastname": "Admin",
      "username": "admin",
      "password": "admin@123",
      "email": "admin@mail.com",
      "userrole": "Admin"
    }
  ],
  "products": [
    {
      "id": "1",
      "name": "Xiaomi Pad 6",
      "price": "30,000",
      "desc": "Xiaomi Pad 6 having Snapdragon 870 Octa-Core Processor",
      "image": "/assets/Tablet1.jpg"
    },
    {
      "id": "2",
      "name": "Samsung",
      "price": "62,000",
      "desc": "Samsung having Snapdragon 870 Octa-Core Processor",
      "image": "/assets/Tablet2.jpg"
    },
    {
      "id": "3",
      "name": "Moto",
      "desc": "Moto having Snapdragon 870 Octa-Core Processor",
      "image": "/assets/Tablet3.jpg",
      "price": "34,000"
    },
    {
      "id": "4",
      "name": "Honor",
      "desc": "Honor having Snapdragon 870 Octa-Core Processor",
      "image": "/assets/Tablet4.jpg",
      "price": "45,000"
    },
    {
      "id": "5",
      "name": "Vivo",
      "desc": "Vivo having Snapdragon 870 Octa-Core Processor",
      "image": "/assets/Tablet5.jpg",
      "price": "57,000"
    },
    {
      "id": "6",
      "name": "Apple",
      "desc": "Apple having Snapdragon 870 Octa-Core Processor",
      "image": "/assets/Tablet7.jpg",
      "price": "45,000"
    },
    {
      "id": "7",
      "name": "Samsung",
      "desc": "Samsung having Snapdragon 870 Octa-Core Processor",
      "image": "/assets/Tablet8.jpg",
      "price": "1,12,000"
    },
    {
      "id": "8",
      "name": "Lenovo",
      "price": "65,000",
      "desc": "Lenovo having Snapdragon 870 Octa-Core Processor",
      "image": "/assets/Tablet9.jpg"
    },
    {
      "id": "9",
      "name": "Oppo",
      "price": "35,000",
      "desc": "Oppo having Snapdragon 870 Octa-Core Processor",
      "image": "/assets/Tablet10.jpg"
    },
    {
      "id": "11",
      "name": "Apple i-pad",
      "price": "70000",
      "desc": "Having Good Functionalities",
      "image": "https://m.media-amazon.com/images/I/81gC7frRJyL._SX679_.jpg"
    },
    {
      "id": "12",
      "name": "Samsung S8",
      "price": "65000",
      "desc": "The product having the extra battery performance and more stability",
      "image": "https://m.media-amazon.com/images/I/81Vs371KLML._AC_UY218_.jpg"
    }
  ]
}